setup.py
Flask_Imagine_S3Adapter.egg-info/PKG-INFO
Flask_Imagine_S3Adapter.egg-info/SOURCES.txt
Flask_Imagine_S3Adapter.egg-info/dependency_links.txt
Flask_Imagine_S3Adapter.egg-info/not-zip-safe
Flask_Imagine_S3Adapter.egg-info/requires.txt
Flask_Imagine_S3Adapter.egg-info/top_level.txt
flask_imagine_s3_adapter/__init__.py