Metadata-Version: 1.1
Name: Flask-Imagine-S3Adapter
Version: 0.4
Summary: Amazon AWS S3 adapter for Flask-Imagine extension.
Home-page: https://github.com/FlaskGuys/Flask-Imagine-S3Adapter
Author: Kronas
Author-email: kronas.sw@gmail.com
License: MIT
Platform: UNKNOWN
Classifier: Development Status :: 4 - Beta
Classifier: Intended Audience :: Developers
Classifier: License :: OSI Approved :: MIT License
Classifier: Natural Language :: English
Classifier: Operating System :: OS Independent
Classifier: Programming Language :: Python :: 2
Classifier: Topic :: Software Development :: Libraries :: Python Modules
